discord_interactions_flask/__init__.py
discord_interactions_flask/command.py
discord_interactions_flask/command_builder.py
discord_interactions_flask/components.py
discord_interactions_flask/discord.py
discord_interactions_flask/discord_types.py
discord_interactions_flask/errors.py
discord_interactions_flask/helpers.py
discord_interactions_flask/interactions.py
discord_interactions_flask/jsons.py
discord_interactions_flask/verify.py
discord_interactions_flask-0.1.1.dist-info/LICENSE
discord_interactions_flask-0.1.1.dist-info/WHEEL
discord_interactions_flask-0.1.1.dist-info/METADATA
discord_interactions_flask-0.1.1.dist-info/RECORD
