Metadata-Version: 2.1
Name: discord-interactions-flask
Version: 0.1.1
Summary: 
Home-page: https://github.com/buckley-w-david/discord-interactions-flask
License: MIT
Author: David Buckley
Author-email: david@davidbuckley.ca
Requires-Python: >=3.10,<4.0
Classifier: License :: OSI Approved :: MIT License
Classifier: Programming Language :: Python :: 3
Classifier: Programming Language :: Python :: 3.10
Requires-Dist: Flask (>=2.1.3,<3.0.0)
Requires-Dist: PyNaCl (>=1.5.0,<2.0.0)
Requires-Dist: jsons (>=1.6.3,<2.0.0)
Requires-Dist: urllib3 (>=1.26.10,<2.0.0)
Project-URL: Repository, https://github.com/buckley-w-david/discord-interactions-flask
